{
  "i1": { "x": 100, "y": 20, "z": 20 },
  "i2": { "x": 10, "y": 120, "z": 10 },
  "o1": { "x": -7, "y": -3, "z": -8 },
  "o2": { "x": 6, "y": 1, "z": -9 },
  "pl1": { "x": 5, "y": 5, "z": 10 },
  "pl2": { "x": -5, "y": 0, "z": 10 },
  "p0": { "x": -6, "y": 0, "z": 0 },
  "p1": { "x": 0, "y": 7, "z": 0 },
  "p2": { "x": 2, "y": -2, "z": 1 },
  "xs": [0.5, 1, 1.5, 2, 2.5],
  "ys": [0.5, 1, 1.5, 2, 2.5],
  "v": { "x": -8, "y": 8, "z": 10 },
  "k": { "x": 20, "y": 20, "z": 20 },
  "k_d": 0.8,
  "k_s": 0.5,
  "k_e": 10
}